{
  "videos": [
    {
      "uri": "photos_and_videos/videos/73318702_2453630198239775_496751506523947008_n_1953687184777975.mp4",
      "creation_timestamp": 1571105132,
      "media_metadata": {
        "video_metadata": {
          "upload_timestamp": 0,
          "upload_ip": "39.50.241.235"
        }
      },
      "thumbnail": {
        "uri": "photos_and_videos/videos/73318702_2453630198239775_496751506523947008_n_1953687184777975.mp4"
      },
      "title": "Kabeers Network Services",
      "description": "Best of Kabeers Net For you. Pastpapers , Compiler, QnA, Search, Movies"
    },
    {
      "uri": "photos_and_videos/videos/104760042_347973952855234_4301378781096971301_n_787796005074113.mp4",
      "creation_timestamp": 1580394780,
      "media_metadata": {
        "video_metadata": {
          "upload_timestamp": 0,
          "upload_ip": "39.50.144.194"
        }
      },
      "thumbnail": {
        "uri": "photos_and_videos/videos/104760042_347973952855234_4301378781096971301_n_787796005074113.mp4"
      },
      "title": "Kabeers Music- Music App with Free Download",
      "description": "Get Kabeers Music Now For Mobile Deskotp or Web & Access your Favourite Songs + Download Them."
    },
    {
      "uri": "photos_and_videos/videos/104409780_115744849965744_610797877433010362_n_1061883660832799.mp4",
      "creation_timestamp": 1580415984,
      "media_metadata": {
        "video_metadata": {
          "upload_timestamp": 0,
          "upload_ip": "39.50.235.118"
        }
      },
      "thumbnail": {
        "uri": "photos_and_videos/videos/104409780_115744849965744_610797877433010362_n_1061883660832799.mp4"
      },
      "title": "Kabeer Music- Builtin Song Recognition",
      "description": "Recognize Music Playing Near You with the new Kabeer Music App For Android."
    },
    {
      "uri": "photos_and_videos/videos/84684623_497205511178772_4543203894469066752_n_1241892906201172.mp4",
      "creation_timestamp": 1580504296,
      "media_metadata": {
        "video_metadata": {
          "upload_timestamp": 0,
          "upload_ip": "39.50.175.236"
        }
      },
      "thumbnail": {
        "uri": "photos_and_videos/videos/84684623_497205511178772_4543203894469066752_n_1241892906201172.mp4"
      },
      "title": "Kabeers Network - How Many Services Do We Have?",
      "description": "Find out More About Our Services From Our Home Page kabeersnetwork.dx.am"
    },
    {
      "uri": "photos_and_videos/videos/85701810_1203373539859094_697191213547126784_n_966098613792294.mp4",
      "creation_timestamp": 1581507620,
      "media_metadata": {
        "video_metadata": {
          "upload_timestamp": 0,
          "upload_ip": "39.50.188.173"
        }
      },
      "thumbnail": {
        "uri": "photos_and_videos/videos/85701810_1203373539859094_697191213547126784_n_966098613792294.mp4"
      },
      "title": "Kabeers Music - Try Kabeers Music its Free",
      "description": "Kabeer's Music Stable V3.4 is out now! Enjoy it offline with 75% faster loading times."
    },
    {
      "uri": "photos_and_videos/videos/86382310_637852173694483_2734297002358603776_n_577429582811364.mp4",
      "creation_timestamp": 1581525006,
      "media_metadata": {
        "video_metadata": {
          "upload_timestamp": 0,
          "upload_ip": "39.50.184.215"
        }
      },
      "thumbnail": {
        "uri": "photos_and_videos/videos/86382310_637852173694483_2734297002358603776_n_577429582811364.mp4"
      },
      "title": "Kabeers Music - V3.3 vs V3.4 BETA Speed test Comparison",
      "description": "Kabeer's Music Stable V3.4 BETA is out now! Enjoy it offline with 75% faster loading times."
    },
    {
      "uri": "photos_and_videos/videos/87829541_661834817909599_8889985675928010752_n_206880060399567.mp4",
      "creation_timestamp": 1584097181,
      "media_metadata": {
        "video_metadata": {
          "upload_timestamp": 0,
          "upload_ip": "39.50.215.54"
        }
      },
      "thumbnail": {
        "uri": "photos_and_videos/videos/87829541_661834817909599_8889985675928010752_n_206880060399567.mp4"
      },
      "title": "Kabeers Search - Fast and Secure is Out Now!",
      "description": "Kabeer's Search fast and secure is out now. For free try it get work done!\n\nMusic: \"Aslan Gibi\" by sila"
    },
    {
      "uri": "photos_and_videos/videos/103482033_261263358284973_708616805121631743_n_1090137204712291.mp4",
      "creation_timestamp": 1584477005,
      "media_metadata": {
        "video_metadata": {
          "upload_timestamp": 0,
          "upload_ip": "39.50.236.215"
        }
      },
      "thumbnail": {
        "uri": "photos_and_videos/videos/103482033_261263358284973_708616805121631743_n_1090137204712291.mp4"
      },
      "title": "Kabeers Drive - Free Unlimited Secure Cloud Storage For All",
      "description": "Kabeers Drive is out now. Store any file create Folders share , collabroate and edit all on the cloud. Visit kabeersdrive.ueuo.com/api/ for developer info"
    },
    {
      "uri": "photos_and_videos/videos/92692768_999649527095839_3861816833940186959_n_290726561900036.mp4",
      "creation_timestamp": 1584705240,
      "media_metadata": {
        "video_metadata": {
          "upload_timestamp": 1584705226
        }
      },
      "thumbnail": {
        "uri": "photos_and_videos/videos/92692768_999649527095839_3861816833940186959_n_290726561900036.mp4"
      },
      "title": "The New Kabeer Search - Fast and Secure is out Now",
      "description": "Crawl around the web faster and more secure with the new Kabeer Search"
    },
    {
      "uri": "photos_and_videos/videos/94483361_668706120589500_2569331147775176178_n_254451618938627.mp4",
      "creation_timestamp": 1587850314,
      "media_metadata": {
        "video_metadata": {
          "upload_timestamp": 0,
          "upload_ip": "39.50.249.225"
        }
      },
      "thumbnail": {
        "uri": "photos_and_videos/videos/94483361_668706120589500_2569331147775176178_n_254451618938627.mp4"
      },
      "title": "Kabeers Network The Movie is Comming out soon",
      "description": "More info on our Facebook Page! facebook.com/kabeers.network ."
    },
    {
      "uri": "photos_and_videos/videos/99252977_633994510521451_4233718846729740332_n_266856004451132.mp4",
      "creation_timestamp": 1589726187,
      "media_metadata": {
        "video_metadata": {
          "upload_timestamp": 0,
          "upload_ip": "39.50.229.3"
        }
      },
      "thumbnail": {
        "uri": "photos_and_videos/videos/99252977_633994510521451_4233718846729740332_n_266856004451132.mp4"
      },
      "title": "Kabeers Drive Has Been Updated Added New Features",
      "description": "Kabeers Drive Has Been Updated Added Folder Sharing and Drag and Drop File Selection System to take Group Actions on files and folders"
    },
    {
      "uri": "photos_and_videos/videos/102279144_2301482613479696_8613919607827637146_n_903349276835660.mp4",
      "creation_timestamp": 1591340523,
      "media_metadata": {
        "video_metadata": {
          "upload_timestamp": 0,
          "upload_ip": "39.50.255.231"
        }
      },
      "thumbnail": {
        "uri": "photos_and_videos/videos/102279144_2301482613479696_8613919607827637146_n_903349276835660.mp4"
      },
      "title": "Kabeers Drive Landing Page has been updated added more API Docs",
      "description": "Kabeers Drive home page has been Updated."
    }
  ]
}
